build/lib/more_admin_filters/__init__.py
build/lib/more_admin_filters/__version__.py
build/lib/more_admin_filters/apps.py
build/lib/more_admin_filters/filters.py
build/lib/tests/testapp/__init__.py
build/lib/tests/testapp/admin.py
build/lib/tests/testapp/apps.py
build/lib/tests/testapp/models.py
build/lib/tests/testapp/settings.py
build/lib/tests/testapp/urls.py
build/lib/tests/testapp/wsgi.py
build/lib/tests/testapp/management/__init__.py
build/lib/tests/testapp/management/commands/__init__.py
build/lib/tests/testapp/management/commands/createtestdata.py
build/lib/tests/testapp/migrations/0001_initial.py
build/lib/tests/testapp/migrations/0002_modela_multiselect_utf8.py
build/lib/tests/testapp/migrations/__init__.py
build/lib/tests/testapp/tests/__init__.py
build/lib/tests/testapp/tests/test_filters.py
build/lib/tests/testapp/tests/test_live_filters.py
django_more_admin_filters-1.15.dist-info/licenses/LICENSE
more_admin_filters/__init__.py
more_admin_filters/__version__.py
more_admin_filters/apps.py
more_admin_filters/filters.py
more_admin_filters/templates/more_admin_filters/dropdownfilter.html
more_admin_filters/templates/more_admin_filters/multiselectdropdownfilter.html
tests/testapp/__init__.py
tests/testapp/admin.py
tests/testapp/apps.py
tests/testapp/models.py
tests/testapp/settings.py
tests/testapp/urls.py
tests/testapp/wsgi.py
tests/testapp/management/__init__.py
tests/testapp/management/commands/__init__.py
tests/testapp/management/commands/createtestdata.py
tests/testapp/migrations/0001_initial.py
tests/testapp/migrations/0002_modela_multiselect_utf8.py
tests/testapp/migrations/__init__.py
tests/testapp/tests/__init__.py
tests/testapp/tests/test_filters.py
tests/testapp/tests/test_live_filters.py
django_more_admin_filters-1.15.dist-info/METADATA
django_more_admin_filters-1.15.dist-info/WHEEL
django_more_admin_filters-1.15.dist-info/top_level.txt
django_more_admin_filters-1.15.dist-info/zip-safe
django_more_admin_filters-1.15.dist-info/RECORD
